<annotation>
	<folder>trainfoto</folder>
	<filename>wytze_imgA (28).jpg</filename>
	<path>C:\Users\Ikke\Desktop\wytze trainfoto\trainfoto\wytze_imgA (28).jpg</path>
	<source>
		<database>Unknown</database>
	</source>
	<size>
		<width>664</width>
		<height>374</height>
		<depth>3</depth>
	</size>
	<segmented>0</segmented>
	<object>
		<name>tray_right</name>
		<pose>Unspecified</pose>
		<truncated>1</truncated>
		<difficult>0</difficult>
		<bndbox>
			<xmin>133</xmin>
			<ymin>18</ymin>
			<xmax>431</xmax>
			<ymax>374</ymax>
		</bndbox>
	</object>
	<object>
		<name>tray_front</name>
		<pose>Unspecified</pose>
		<truncated>1</truncated>
		<difficult>0</difficult>
		<bndbox>
			<xmin>1</xmin>
			<ymin>94</ymin>
			<xmax>188</xmax>
			<ymax>374</ymax>
		</bndbox>
	</object>
</annotation>
